tablex/__init__.py
tablex/converter.py
tablexpy-0.1.0.dist-info/licenses/LICENSE
tablexpy-0.1.0.dist-info/METADATA
tablexpy-0.1.0.dist-info/WHEEL
tablexpy-0.1.0.dist-info/top_level.txt
tablexpy-0.1.0.dist-info/RECORD
