Metadata-Version: 2.4
Name: tablexpy
Version: 0.1.0
Summary: A simple Python library to convert between CSV, JSON, and Excel easily.
Author-email: Samartha M J <sammjsagar@gmail.com>
License: MIT
Requires-Python: >=3.7
License-File: LICENSE
Requires-Dist: pandas>=1.0.0
Requires-Dist: openpyxl>=3.0.0
Dynamic: license-file
